woe_conversion/__init__.py
woe_conversion/woe.py
woe_conversion/woe.py~
woe_conversion-0.1.1.dist-info/METADATA
woe_conversion-0.1.1.dist-info/WHEEL
woe_conversion-0.1.1.dist-info/licenses/LICENSE
woe_conversion-0.1.1.dist-info/licenses/LICENSE~
woe_conversion-0.1.1.dist-info/RECORD
