Metadata-Version: 2.3
Name: woe_conversion
Version: 0.1.1
Summary: woe is a Python library designed to convert categorical and continuous variables into weight of evidence. Weight of evidence is a statistical technique used in information theory to measure the strength of a relationship between a binary target variable and a predictor variable. The library can be used for data preprocessing in predictive modeling or machine learning projects.
Project-URL: Homepage, https://github.com/BertrandBrelier/woe
Project-URL: Bug Tracker, https://github.com/BertrandBrelier/woe
Author-email: Bertrand Brelier <bertrand.brelier@gmail.com>
License-File: LICENSE
License-File: LICENSE~
Classifier: License :: OSI Approved :: MIT License
Classifier: Operating System :: OS Independent
Classifier: Programming Language :: Python :: 3
Requires-Python: >=3.7
